dirhunt/__init__.py
dirhunt/_compat.py
dirhunt/agents.py
dirhunt/cli.py
dirhunt/colors.py
dirhunt/crawler.py
dirhunt/crawler_url.py
dirhunt/directory_lists.py
dirhunt/exceptions.py
dirhunt/json_report.py
dirhunt/management.py
dirhunt/output.py
dirhunt/pool.py
dirhunt/processors.py
dirhunt/sessions.py
dirhunt/url.py
dirhunt/url_info.py
dirhunt/url_loop.py
dirhunt/utils.py
dirhunt/sources/__init__.py
dirhunt/sources/base.py
dirhunt/sources/commoncrawl.py
dirhunt/sources/crtsh.py
dirhunt/sources/google.py
dirhunt/sources/robots.py
dirhunt/sources/ssl.py
dirhunt/sources/virustotal.py
dirhunt/sources/wayback.py
dirhunt/tests/__init__.py
dirhunt/tests/_compat.py
dirhunt/tests/base.py
dirhunt/tests/test_colors.py
dirhunt/tests/test_crawler.py
dirhunt/tests/test_crawler_url.py
dirhunt/tests/test_directory_lists.py
dirhunt/tests/test_exceptions.py
dirhunt/tests/test_processors.py
dirhunt/tests/test_sessions.py
dirhunt/tests/test_sources.py
dirhunt/tests/test_url_info.py
dirhunt/tests/test_url_loop.py
dirhunt/tests/test_utils.py
dirhunt-1.0.0.data/scripts/dirhunt
dirhunt-1.0.0.dist-info/AUTHORS.rst
dirhunt-1.0.0.dist-info/LICENSE.txt
dirhunt-1.0.0.dist-info/METADATA
dirhunt-1.0.0.dist-info/WHEEL
dirhunt-1.0.0.dist-info/entry_points.txt
dirhunt-1.0.0.dist-info/pbr.json
dirhunt-1.0.0.dist-info/top_level.txt
dirhunt-1.0.0.dist-info/RECORD
