Metadata-Version: 2.1
Name: dirhunt
Version: 1.0.0
Summary: Find web directories without bruteforce
Home-page: https://github.com/Nekmo/dirhunt
Download-URL: https://github.com/Nekmo/dirhunt/archive/master.zip
Author: Nekmo
Author-email: contacto@nekmo.com
Keywords: directories,websec,pentesting,security-audit
Platform: linux
Classifier: License :: OSI Approved :: MIT License
Classifier: Operating System :: POSIX :: Linux
Classifier: Programming Language :: Python :: 2.7
Classifier: Programming Language :: Python :: 3.7
Classifier: Programming Language :: Python :: 3.8
Classifier: Programming Language :: Python :: 3.9
Classifier: Programming Language :: Python :: 3.10
Classifier: Programming Language :: Python :: 3.11
Classifier: Programming Language :: Python :: 3.12
Classifier: Natural Language :: English
Classifier: Development Status :: 3 - Alpha
Provides: dirhunt
License-File: LICENSE.txt
License-File: AUTHORS.rst
